LICENSE
README.md
setup.py
Classification/__init__.py
Classification/Attribute/Attribute.py
Classification/Attribute/AttributeType.py
Classification/Attribute/BinaryAttribute.py
Classification/Attribute/ContinuousAttribute.py
Classification/Attribute/DiscreteAttribute.py
Classification/Attribute/DiscreteIndexedAttribute.py
Classification/Attribute/__init__.py
Classification/DataSet/DataDefinition.py
Classification/DataSet/DataSet.py
Classification/DataSet/__init__.py
Classification/DistanceMetric/DistanceMetric.py
Classification/DistanceMetric/EuclidianDistance.py
Classification/DistanceMetric/MahalanobisDistance.py
Classification/DistanceMetric/__init__.py
Classification/Experiment/BootstrapRun.py
Classification/Experiment/Experiment.py
Classification/Experiment/KFoldRun.py
Classification/Experiment/KFoldRunSeparateTest.py
Classification/Experiment/MultipleRun.py
Classification/Experiment/MxKFoldRun.py
Classification/Experiment/MxKFoldRunSeparateTest.py
Classification/Experiment/SingleRun.py
Classification/Experiment/SingleRunWithK.py
Classification/Experiment/StratifiedKFoldRun.py
Classification/Experiment/StratifiedKFoldRunSeparateTest.py
Classification/Experiment/StratifiedMxKFoldRun.py
Classification/Experiment/StratifiedMxKFoldRunSeparateTest.py
Classification/Experiment/StratifiedSingleRunWithK.py
Classification/Experiment/__init__.py
Classification/FeatureSelection/BackwardSelection.py
Classification/FeatureSelection/FeatureSubSet.py
Classification/FeatureSelection/FloatingSelection.py
Classification/FeatureSelection/ForwardSelection.py
Classification/FeatureSelection/SubSetSelection.py
Classification/FeatureSelection/__init__.py
Classification/Filter/DiscreteToContinuous.py
Classification/Filter/DiscreteToIndexed.py
Classification/Filter/FeatureFilter.py
Classification/Filter/LaryFilter.py
Classification/Filter/LaryToBinary.py
Classification/Filter/Normalize.py
Classification/Filter/Pca.py
Classification/Filter/TrainedFeatureFilter.py
NlpToolkit_Classification.egg-info/PKG-INFO
NlpToolkit_Classification.egg-info/SOURCES.txt
NlpToolkit_Classification.egg-info/dependency_links.txt
NlpToolkit_Classification.egg-info/requires.txt
NlpToolkit_Classification.egg-info/top_level.txt