Metadata-Version: 2.1
Name: NlpToolkit-Classification
Version: 1.0.17
Summary: Classification library
Home-page: https://github.com/StarlangSoftware/Classification-Py
Author: olcaytaner
Author-email: olcay.yildiz@ozyegin.edu.tr
License: UNKNOWN
Platform: UNKNOWN
